cfncli/__init__.py
cfncli/__main__.py
cfncli/cli/__init__.py
cfncli/cli/autocomplete.py
cfncli/cli/context.py
cfncli/cli/main.py
cfncli/cli/multicommand.py
cfncli/cli/types.py
cfncli/cli/commands/__init__.py
cfncli/cli/commands/drift/__init__.py
cfncli/cli/commands/drift/drift.py
cfncli/cli/commands/drift/detect/__init__.py
cfncli/cli/commands/drift/detect/detect.py
cfncli/cli/commands/drift/diff/__init__.py
cfncli/cli/commands/drift/diff/diff.py
cfncli/cli/commands/export/__init__.py
cfncli/cli/commands/export/export.py
cfncli/cli/commands/generate/__init__.py
cfncli/cli/commands/generate/generate.py
cfncli/cli/commands/stack/__init__.py
cfncli/cli/commands/stack/stack.py
cfncli/cli/commands/stack/cancel/__init__.py
cfncli/cli/commands/stack/cancel/cancel.py
cfncli/cli/commands/stack/changeset/__init__.py
cfncli/cli/commands/stack/changeset/changeset.py
cfncli/cli/commands/stack/changeset/create/__init__.py
cfncli/cli/commands/stack/changeset/create/create.py
cfncli/cli/commands/stack/changeset/exec/__init__.py
cfncli/cli/commands/stack/changeset/exec/exec.py
cfncli/cli/commands/stack/delete/__init__.py
cfncli/cli/commands/stack/delete/delete.py
cfncli/cli/commands/stack/deploy/__init__.py
cfncli/cli/commands/stack/deploy/deploy.py
cfncli/cli/commands/stack/describe/__init__.py
cfncli/cli/commands/stack/describe/describe.py
cfncli/cli/commands/stack/sync/__init__.py
cfncli/cli/commands/stack/sync/sync.py
cfncli/cli/commands/stack/tail/__init__.py
cfncli/cli/commands/stack/tail/tail.py
cfncli/cli/commands/stack/update/__init__.py
cfncli/cli/commands/stack/update/update.py
cfncli/cli/commands/status/__init__.py
cfncli/cli/commands/status/status.py
cfncli/cli/commands/validate/__init__.py
cfncli/cli/commands/validate/validate.py
cfncli/cli/utils/__init__.py
cfncli/cli/utils/colormaps.py
cfncli/cli/utils/common.py
cfncli/cli/utils/deco.py
cfncli/cli/utils/events.py
cfncli/cli/utils/pager.py
cfncli/cli/utils/pprint.py
cfncli/config/__init__.py
cfncli-0.6.3.dist-info/licenses/LICENSE
cfncli-0.6.3.dist-info/METADATA
cfncli-0.6.3.dist-info/WHEEL
cfncli-0.6.3.dist-info/entry_points.txt
cfncli-0.6.3.dist-info/top_level.txt
cfncli-0.6.3.dist-info/RECORD
