Metadata-Version: 2.4
Name: cfncli
Version: 0.6.3
Summary: CloudFormation CLI Wrapper
Author-email: "Fase, Andy" <andyfase@gmail.com>
Project-URL: Homepage, https://github.com/andyfase/cfncli
Keywords: aws,cfn,cli,cloudformation,changeset,sam,serverless
Classifier: Development Status :: 5 - Production/Stable
Classifier: Environment :: Console
Classifier: Programming Language :: Python :: 3.9
Classifier: Programming Language :: Python :: 3.10
Classifier: Intended Audience :: Developers
Classifier: Intended Audience :: System Administrators
Classifier: Topic :: Internet
Classifier: Topic :: Software Development :: Build Tools
Classifier: Topic :: Utilities
Requires-Python: >=3.10
License-File: LICENSE
Requires-Dist: backoff>=2.2
Requires-Dist: boto3>=1.39
Requires-Dist: botocore>=1.39
Requires-Dist: click>=8.2
Requires-Dist: colorama>=0.4
Requires-Dist: jsonschema>=4.0
Requires-Dist: pyyaml>=6.0
Requires-Dist: s3transfer>=0.13
Requires-Dist: deepmerge>=2.0
Dynamic: license-file
